orko/__init__.py
orko/_version.py
orko/cli/__init__.py
orko/core/__init__.py
orko/core/base.py
orko/core/env.py
orko/core/process.py
orko-0.1.0.dist-info/LICENSE
orko-0.1.0.dist-info/METADATA
orko-0.1.0.dist-info/WHEEL
orko-0.1.0.dist-info/entry_points.txt
orko-0.1.0.dist-info/top_level.txt
orko-0.1.0.dist-info/RECORD
